<NoRules>

  


   


        <item>et merde<tag>data.val="1"</tag></item>
        <item>ta gueule<tag>data.val="1"</tag></item>
        <item>oh putin de merde<tag>data.val="1"</tag></item>
        <item>putin de merde<tag>data.val="1"</tag></item>
        <item>ta gueule<tag>data.val="1"</tag></item>
        <item>putin<tag>data.val="1"</tag></item>
        <item>putin<tag>data.val="1"</tag></item>
        <item>abruti<tag>data.val="1"</tag></item>

        <item>andouille<tag>data.val="1"</tag></item>
       
        <item>connard<tag>data.val="1"</tag></item>
        <item>trou du cul<tag>data.val="1"</tag></item>
        <item>enfoiré<tag>data.val="1"</tag></item>
        <item>bordel<tag>data.val="1"</tag></item>
     

        <item>il y a quelqu'un<tag>data.val="2"</tag></item>
        <item>qui est là<tag>data.val="2"</tag></item>

        <item>silence<tag>data.val="3"</tag></item>
          
        <item>du calme<tag>data.val="4"</tag></item>
        <item>waouh<tag>data.val="4"</tag></item>
        <item>Warcq <tag>data.val="4"</tag></item>
        
        <item>ça suffit<tag>data.val="5"</tag></item> 

        <item>ça marche pas<tag>data.val="6"</tag></item>
        <item>ça plante<tag>data.val="6"</tag></item>

       
        <item>c'est quoi ce bordel<tag>data.val="7"</tag></item>

    


